{
  "domains": ["crm", "email", "storage", "analytics", "auth", "scheduling"],
  "entities": ["catpaw", "catflow", "canvas", "catbrain", "connector", "skill", "template"],
  "modes": ["chat", "processor", "hybrid"],
  "connectors": ["gmail", "holded", "drive", "mcp", "http", "n8n", "smtp"],
  "roles": ["extractor", "transformer", "synthesizer", "renderer", "emitter", "guard", "reporter"],
  "departments": ["business", "finance", "production", "other"],
  "rules": ["R01", "R02", "R03", "R04", "R05", "R06", "R07", "R08", "R09", "R10", "R11", "R12", "R13", "R14", "R15", "R16", "R17", "R18", "R19", "R20", "R21", "R22", "R23", "R24", "R25", "SE01", "SE02", "SE03", "DA01", "DA02", "DA03", "DA04"],
  "cross_cutting": ["safety", "performance", "learning", "ux", "ops", "testing"]
}
